ngiri/__init__.py
ngiri/__version__.py
ngiri/_api.py
ngiri/_auth.py
ngiri/_client.py
ngiri/_compat.py
ngiri/_config.py
ngiri/_content.py
ngiri/_decoders.py
ngiri/_exceptions.py
ngiri/_main.py
ngiri/_models.py
ngiri/_multipart.py
ngiri/_status_codes.py
ngiri/_types.py
ngiri/_urlparse.py
ngiri/_urls.py
ngiri/_utils.py
ngiri/py.typed
ngiri/_transports/__init__.py
ngiri/_transports/asgi.py
ngiri/_transports/base.py
ngiri/_transports/default.py
ngiri/_transports/mock.py
ngiri/_transports/wsgi.py
ngiri-0.0.3.dist-info/METADATA
ngiri-0.0.3.dist-info/WHEEL
ngiri-0.0.3.dist-info/entry_points.txt
ngiri-0.0.3.dist-info/licenses/LICENSE
ngiri-0.0.3.dist-info/licenses/LICENSE.md
ngiri-0.0.3.dist-info/RECORD
